vizeval/__init__.py
vizeval/client.py
vizeval/evaluators.py
vizeval/exceptions.py
vizeval/models.py
vizeval/openai_wrapper.py
vizeval-0.1.1.dist-info/METADATA
vizeval-0.1.1.dist-info/WHEEL
vizeval-0.1.1.dist-info/top_level.txt
vizeval-0.1.1.dist-info/RECORD
